simple_regex_generator/.DS_Store
simple_regex_generator/.gitignore
simple_regex_generator/__init__.py
simple_regex_generator/config/.DS_Store
simple_regex_generator/config/config.json
simple_regex_generator/config/definition__regex.json
simple_regex_generator/init.py
simple_regex_generator/libs/.DS_Store
simple_regex_generator/libs/.gitignore
simple_regex_generator/libs/__init__.py
simple_regex_generator/libs/create_regex_collections.py
simple_regex_generator/libs/generator.py
simple_regex_generator/libs/select_regex.py
simple_regex_generator-0.1.0.dist-info/METADATA
simple_regex_generator-0.1.0.dist-info/WHEEL
simple_regex_generator-0.1.0.dist-info/RECORD
