Metadata-Version: 2.1
Name: simple-regex-generator
Version: 0.1.0
Summary: This module is to generate simple regex pattern from string
Author: Tomoya Wada
Author-email: tomoyawada@gmail.com
Requires-Python: >=3.9,<4.0
Classifier: Programming Language :: Python :: 3
Classifier: Programming Language :: Python :: 3.9
Classifier: Programming Language :: Python :: 3.10
Classifier: Programming Language :: Python :: 3.11
